matchscraper/__init__.py
matchscraper/items.py
matchscraper/main.py
matchscraper/middlewares.py
matchscraper/pipelines.py
matchscraper/settings.py
matchscraper/utils.py
matchscraper/version.py
matchscraper/spiders/__init__.py
matchscraper/spiders/competition.py
matchscraper/spiders/match.py
matchscraper-0.2.1.1.dist-info/LICENSE.md
matchscraper-0.2.1.1.dist-info/METADATA
matchscraper-0.2.1.1.dist-info/WHEEL
matchscraper-0.2.1.1.dist-info/entry_points.txt
matchscraper-0.2.1.1.dist-info/top_level.txt
matchscraper-0.2.1.1.dist-info/RECORD
