Metadata-Version: 2.1
Name: matchscraper
Version: 0.2.1.1
Summary: CLI tool to get volleyball match statistics from the Web Competition by Data Project websites
Home-page: https://github.com/claromes/matchscraper
Author: claromes
License: UNKNOWN
Project-URL: Documentation, https://claromes.github.io/matchscraper/
Project-URL: Issue Tracker, https://github.com/claromes/matchscraper/issues
Keywords: volleyball sports cli dataset analytics
Platform: UNKNOWN
Classifier: Development Status :: 4 - Beta
Classifier: Environment :: Console
Classifier: Framework :: Scrapy
Classifier: Intended Audience :: Science/Research
Classifier: Intended Audience :: Developers
Classifier: License :: OSI Approved :: GNU General Public License v3 (GPLv3)
Classifier: Operating System :: OS Independent
Classifier: Programming Language :: Python
Classifier: Programming Language :: Python :: 3.8
Classifier: Topic :: Scientific/Engineering
Classifier: Topic :: Scientific/Engineering :: Information Analysis
Classifier: Topic :: Utilities
Requires-Python: >=3.8
Requires-Dist: scrapy (==2.7.1)
